Metadata-Version: 2.1
Name: TCL-TV-Remote
Version: 0.0.1
Summary: Remote control for TCL Smart TVs
Home-page: https://github.com/popeen/TCL-TV-Remote
Author: Patrik Johansson
Author-email: tcltvremote@popeen.com
Classifier: Programming Language :: Python :: 3
Classifier: License :: OSI Approved :: MIT License
Classifier: Operating System :: OS Independent
Requires-Python: >=3.6
License-File: LICENSE.md
